cooler/__init__.py
cooler/__main__.py
cooler/_balance.py
cooler/_logging.py
cooler/_reduce.py
cooler/_typing.py
cooler/_version.py
cooler/api.py
cooler/fileops.py
cooler/parallel.py
cooler/util.py
cooler/cli/__init__.py
cooler/cli/_util.py
cooler/cli/balance.py
cooler/cli/cload.py
cooler/cli/coarsen.py
cooler/cli/csort.py
cooler/cli/digest.py
cooler/cli/dump.py
cooler/cli/fileops.py
cooler/cli/info.py
cooler/cli/load.py
cooler/cli/makebins.py
cooler/cli/merge.py
cooler/cli/show.py
cooler/cli/zoomify.py
cooler/core/__init__.py
cooler/core/_rangequery.py
cooler/core/_selectors.py
cooler/core/_tableops.py
cooler/create/__init__.py
cooler/create/_constants.py
cooler/create/_create.py
cooler/create/_ingest.py
cooler/sandbox/__init__.py
cooler/sandbox/dask.py
cooler-0.10.3.dist-info/METADATA
cooler-0.10.3.dist-info/WHEEL
cooler-0.10.3.dist-info/entry_points.txt
cooler-0.10.3.dist-info/licenses/LICENSE
cooler-0.10.3.dist-info/RECORD
