Metadata-Version: 2.4
Name: cooler
Version: 0.10.3
Summary: Sparse binary format for genomic interaction matrices.
Project-URL: homepage, https://open2c.github.io/cooler
Project-URL: documentation, https://cooler.readthedocs.io
Project-URL: repository, https://github.com/open2c/cooler
Project-URL: changelog, https://github.com/open2c/cooler/blob/master/CHANGES.md
Author-email: Nezar Abdennur <nabdennur@gmail.com>
Maintainer-email: Open2C <open.chromosome.collective@gmail.com>
License: BSD-3-Clause
License-File: LICENSE
Keywords: Hi-C,bioinformatics,contact,format,genomics,hdf5,matrix,sparse
Classifier: Development Status :: 4 - Beta
Classifier: Operating System :: OS Independent
Classifier: Programming Language :: Python
Classifier: Programming Language :: Python :: 3
Classifier: Programming Language :: Python :: 3.9
Classifier: Programming Language :: Python :: 3.10
Classifier: Programming Language :: Python :: 3.11
Classifier: Programming Language :: Python :: 3.12
Requires-Python: >=3.9
Requires-Dist: asciitree
Requires-Dist: click>=7
Requires-Dist: cytoolz
Requires-Dist: h5py>=2.5
Requires-Dist: multiprocess
Requires-Dist: numpy<3,>=1.26
Requires-Dist: pandas>1.5
Requires-Dist: pyfaidx
Requires-Dist: pyyaml
Requires-Dist: scipy>=0.16
Requires-Dist: simplejson
Provides-Extra: all
Requires-Dist: biopython; extra == 'all'
Requires-Dist: dask[array,dataframe]; extra == 'all'
Requires-Dist: ipytree>=0.2.2; extra == 'all'
Requires-Dist: ipywidgets>=8.0.0; extra == 'all'
Requires-Dist: matplotlib; extra == 'all'
Requires-Dist: psutil; extra == 'all'
Requires-Dist: pysam; (platform_system != 'Windows') and extra == 'all'
Provides-Extra: dev
Requires-Dist: biopython; extra == 'dev'
Requires-Dist: coverage[toml]; extra == 'dev'
Requires-Dist: dask[array,dataframe]; extra == 'dev'
Requires-Dist: ipytree>=0.2.2; extra == 'dev'
Requires-Dist: ipywidgets>=8.0.0; extra == 'dev'
Requires-Dist: isort; extra == 'dev'
Requires-Dist: matplotlib; extra == 'dev'
Requires-Dist: pre-commit; extra == 'dev'
Requires-Dist: psutil; extra == 'dev'
Requires-Dist: pysam; (platform_system != 'Windows') and extra == 'dev'
Requires-Dist: pytest; extra == 'dev'
Requires-Dist: pytest-cov; extra == 'dev'
Requires-Dist: ruff; extra == 'dev'
Provides-Extra: docs
Requires-Dist: autodocsumm; extra == 'docs'
Requires-Dist: m2r; extra == 'docs'
Requires-Dist: recommonmark; extra == 'docs'
Requires-Dist: sphinx-autobuild; extra == 'docs'
Requires-Dist: sphinx-rtd-theme; extra == 'docs'
Requires-Dist: sphinx>=1.6; extra == 'docs'
Provides-Extra: test
Requires-Dist: coverage[toml]; extra == 'test'
Requires-Dist: isort; extra == 'test'
Requires-Dist: pytest; extra == 'test'
Requires-Dist: pytest-cov; extra == 'test'
Requires-Dist: ruff; extra == 'test'
